MANIFEST.in
setup.py
QEnvPython310.egg-info/PKG-INFO
QEnvPython310.egg-info/SOURCES.txt
QEnvPython310.egg-info/dependency_links.txt
QEnvPython310.egg-info/top_level.txt
QPT_SDK/__init__.py
QPT_SDK/QEnvPython/__init__.py
QPT_SDK/QEnvPython/python310/LICENSE.txt
QPT_SDK/QEnvPython/python310/_asyncio.pyd
QPT_SDK/QEnvPython/python310/_bz2.pyd
QPT_SDK/QEnvPython/python310/_ctypes.pyd
QPT_SDK/QEnvPython/python310/_decimal.pyd
QPT_SDK/QEnvPython/python310/_elementtree.pyd
QPT_SDK/QEnvPython/python310/_hashlib.pyd
QPT_SDK/QEnvPython/python310/_lzma.pyd
QPT_SDK/QEnvPython/python310/_msi.pyd
QPT_SDK/QEnvPython/python310/_multiprocessing.pyd
QPT_SDK/QEnvPython/python310/_overlapped.pyd
QPT_SDK/QEnvPython/python310/_queue.pyd
QPT_SDK/QEnvPython/python310/_socket.pyd
QPT_SDK/QEnvPython/python310/_sqlite3.pyd
QPT_SDK/QEnvPython/python310/_ssl.pyd
QPT_SDK/QEnvPython/python310/_uuid.pyd
QPT_SDK/QEnvPython/python310/_zoneinfo.pyd
QPT_SDK/QEnvPython/python310/libcrypto-1_1.dll
QPT_SDK/QEnvPython/python310/libffi-7.dll
QPT_SDK/QEnvPython/python310/libssl-1_1.dll
QPT_SDK/QEnvPython/python310/pyexpat.pyd
QPT_SDK/QEnvPython/python310/python.cat
QPT_SDK/QEnvPython/python310/python.exe
QPT_SDK/QEnvPython/python310/python3.dll
QPT_SDK/QEnvPython/python310/python310._pth
QPT_SDK/QEnvPython/python310/python310.dll
QPT_SDK/QEnvPython/python310/python310.zip
QPT_SDK/QEnvPython/python310/pythonw.exe
QPT_SDK/QEnvPython/python310/select.pyd
QPT_SDK/QEnvPython/python310/sqlite3.dll
QPT_SDK/QEnvPython/python310/unicodedata.pyd
QPT_SDK/QEnvPython/python310/vcruntime140.dll
QPT_SDK/QEnvPython/python310/vcruntime140_1.dll
QPT_SDK/QEnvPython/python310/winsound.pyd
QPT_SDK/QEnvPython/python310/Lib/site-packages/distutils-precedence.pth
QPT_SDK/QEnvPython/python310/Lib/site-packages/_distutils_hack/__init__.py
QPT_SDK/QEnvPython/python310/Lib/site-packages/_distutils_hack/override.py
QPT_SDK/QEnvPython/python310/Lib/site-packages/pip/__init__.py
QPT_SDK/QEnvPython/python310/Lib/site-packages/pip/__main__.py
QPT_SDK/QEnvPython/python310/Lib/site-packages/pip/__pip-runner__.py
QPT_SDK/QEnvPython/python310/Lib/site-packages/pip/py.typed
QPT_SDK/QEnvPython/python310/Lib/site-packages/pip-23.3.1.dist-info/AUTHORS.txt
QPT_SDK/QEnvPython/python310/Lib/site-packages/pip-23.3.1.dist-info/INSTALLER
QPT_SDK/QEnvPython/python310/Lib/site-packages/pip-23.3.1.dist-info/LICENSE.txt
QPT_SDK/QEnvPython/python310/Lib/site-packages/pip-23.3.1.dist-info/METADATA
QPT_SDK/QEnvPython/python310/Lib/site-packages/pip-23.3.1.dist-info/RECORD
QPT_SDK/QEnvPython/python310/Lib/site-packages/pip-23.3.1.dist-info/REQUESTED
QPT_SDK/QEnvPython/python310/Lib/site-packages/pip-23.3.1.dist-info/WHEEL
QPT_SDK/QEnvPython/python310/Lib/site-packages/pip-23.3.1.dist-info/entry_points.txt
QPT_SDK/QEnvPython/python310/Lib/site-packages/pip-23.3.1.dist-info/top_level.txt
QPT_SDK/QEnvPython/python310/Lib/site-packages/setuptools-68.2.2.dist-info/INSTALLER
QPT_SDK/QEnvPython/python310/Lib/site-packages/setuptools-68.2.2.dist-info/LICENSE
QPT_SDK/QEnvPython/python310/Lib/site-packages/setuptools-68.2.2.dist-info/METADATA
QPT_SDK/QEnvPython/python310/Lib/site-packages/setuptools-68.2.2.dist-info/RECORD
QPT_SDK/QEnvPython/python310/Lib/site-packages/setuptools-68.2.2.dist-info/REQUESTED
QPT_SDK/QEnvPython/python310/Lib/site-packages/setuptools-68.2.2.dist-info/WHEEL
QPT_SDK/QEnvPython/python310/Lib/site-packages/setuptools-68.2.2.dist-info/entry_points.txt
QPT_SDK/QEnvPython/python310/Lib/site-packages/setuptools-68.2.2.dist-info/top_level.txt
QPT_SDK/QEnvPython/python310/Lib/site-packages/wheel-0.41.3.dist-info/INSTALLER
QPT_SDK/QEnvPython/python310/Lib/site-packages/wheel-0.41.3.dist-info/LICENSE.txt
QPT_SDK/QEnvPython/python310/Lib/site-packages/wheel-0.41.3.dist-info/METADATA
QPT_SDK/QEnvPython/python310/Lib/site-packages/wheel-0.41.3.dist-info/RECORD
QPT_SDK/QEnvPython/python310/Lib/site-packages/wheel-0.41.3.dist-info/REQUESTED
QPT_SDK/QEnvPython/python310/Lib/site-packages/wheel-0.41.3.dist-info/WHEEL
QPT_SDK/QEnvPython/python310/Lib/site-packages/wheel-0.41.3.dist-info/entry_points.txt
