Metadata-Version: 2.1
Name: QEnvPython310
Version: 3.10.10.1
Summary: QPT-Python环境打包工具 Python SDK
Home-page: https://github.com/GT-ZhangAcer/QPT
Author: GT-ZhangAcer
Author-email: zhangacer@foxmail.com
License: MIT
